{
  "town": { "id": "town", "name": "Town", "description": "A relatively safe starting area.", "requiredLevel": 1, "connectedZoneIds": ["crimson_fen", "stonebound_field", "whispering_woods"], "monsterIds": [] },
  "whispering_woods": { "id": "whispering_woods", "name": "Whispering Woods", "description": "A quiet forest near the town.", "requiredLevel": 1, "connectedZoneIds": ["town", "stonebound_field", "burial_grounds"], "monsterIds": ["rat1", "fallen_one", "quill_rat"] },
  "stonebound_field": { "id": "stonebound_field", "name": "Stonebound Field", "description": "Rocky fields.", "requiredLevel": 3, "connectedZoneIds": ["town", "whispering_woods", "crimson_fen", "icy_flats", "arid_plateau"], "monsterIds": ["goblin1", "rat1", "fallen_one", "skeleton_warrior", "fallen_shaman", "corrupt_rogue_archer", "goatman_warrior"] },
  "crimson_fen": { "id": "crimson_fen", "name": "Crimson Fen", "description": "A murky swamp.", "requiredLevel": 5, "connectedZoneIds": ["town", "stonebound_field", "shadow_swamp"], "monsterIds": ["swamp_leech", "fen_lurker", "fetish"] },
  "shadow_swamp": { "id": "shadow_swamp", "name": "Shadow Swamp", "description": "A darker, more dangerous swamp.", "requiredLevel": 8, "connectedZoneIds": ["crimson_fen", "fetid_jungle"], "monsterIds": ["fen_lurker", "ghoul", "wraith", "fetish_shaman"] },
  "icy_flats": { "id": "icy_flats", "name": "Icy Flats", "description": "A frozen wasteland.", "requiredLevel": 10, "connectedZoneIds": ["stonebound_field", "windswept_highland"], "monsterIds": ["wendigo"] },
  "windswept_highland": { "id": "windswept_highland", "name": "Windswept Highland", "description": "High altitude plains.", "requiredLevel": 12, "connectedZoneIds": ["icy_flats", "arid_plateau"], "monsterIds": ["goatman_warrior", "vulture", "saber_cat", "dark_ranger"] },
  "burial_grounds": { "id": "burial_grounds", "name": "Burial Grounds", "description": "An old cemetery overrun by the undead.", "requiredLevel": 2, "connectedZoneIds": ["whispering_woods", "crypt_level_1"], "monsterIds": ["zombie", "skeleton_warrior", "ghoul"] },
  "crypt_level_1": { "id": "crypt_level_1", "name": "Crypt Level 1", "description": "The upper level of a desecrated crypt.", "requiredLevel": 4, "connectedZoneIds": ["burial_grounds", "crypt_level_2"], "monsterIds": ["skeleton_warrior", "skeleton_archer", "ghoul", "wraith"] },
  "crypt_level_2": { "id": "crypt_level_2", "name": "Crypt Level 2", "description": "Deeper within the crypt, ancient horrors stir.", "requiredLevel": 11, "connectedZoneIds": ["crypt_level_1"], "monsterIds": ["wraith", "mummy", "skeleton_archer"] },
  "arid_plateau": { "id": "arid_plateau", "name": "Arid Plateau", "description": "A dry, rocky plateau dotted with sparse vegetation.", "requiredLevel": 9, "connectedZoneIds": ["stonebound_field", "windswept_highland", "forgotten_tombs"], "monsterIds": ["goatman_warrior", "vulture", "sand_maggot", "saber_cat"] },
  "forgotten_tombs": { "id": "forgotten_tombs", "name": "Forgotten Tombs", "description": "Ancient tombs half-buried in the sand.", "requiredLevel": 12, "connectedZoneIds": ["arid_plateau", "tal_rashas_tomb"], "monsterIds": ["mummy", "scarab_demon", "sand_maggot", "greater_mummy", "unraveler"] },
  "fetid_jungle": { "id": "fetid_jungle", "name": "Fetid Jungle", "description": "A dense, humid jungle teeming with aggressive wildlife.", "requiredLevel": 7, "connectedZoneIds": ["shadow_swamp", "spider_forest"], "monsterIds": ["fetish", "fetish_shaman", "saber_cat", "quill_rat", "thorned_hulk"] },
  "lost_city": { "id": "lost_city", "name": "Lost City", "description": "Ruins reclaimed by the desert sands.", "requiredLevel": 16, "connectedZoneIds": ["arid_plateau", "valley_of_snakes"], "monsterIds": ["sand_raider", "vulture", "dark_familiar", "leaper", "blood_hawk"] },
  "valley_of_snakes": { "id": "valley_of_snakes", "name": "Valley of Snakes", "description": "A narrow canyon infested with serpents.", "requiredLevel": 18, "connectedZoneIds": ["lost_city", "claw_viper_temple_lvl1"], "monsterIds": ["pit_viper", "guardian_naga"] },
  "claw_viper_temple_lvl1": { "id": "claw_viper_temple_lvl1", "name": "Claw Viper Temple Lvl 1", "description": "The entrance to an ancient serpentine temple.", "requiredLevel": 20, "connectedZoneIds": ["valley_of_snakes", "claw_viper_temple_lvl2"], "monsterIds": ["guardian_naga", "pit_viper", "temple_guard"] },
  "claw_viper_temple_lvl2": { "id": "claw_viper_temple_lvl2", "name": "Claw Viper Temple Lvl 2", "description": "Deeper within the viper temple.", "requiredLevel": 27, "connectedZoneIds": ["claw_viper_temple_lvl1"], "monsterIds": ["guardian_naga", "hierophant", "temple_guard", "venom_lord"] },
  "harem_level_1": { "id": "harem_level_1", "name": "Harem Level 1", "description": "Opulent, guarded chambers.", "requiredLevel": 17, "connectedZoneIds": ["palace_cellar_lvl1", "harem_level_2"], "monsterIds": ["sand_raider", "succubus", "blunderbore"] },
  "harem_level_2": { "id": "harem_level_2", "name": "Harem Level 2", "description": "Further into the guarded Harem.", "requiredLevel": 18, "connectedZoneIds": ["harem_level_1", "palace_cellar_lvl1"], "monsterIds": ["sand_raider", "succubus", "blunderbore", "dark_familiar"] },
  "palace_cellar_lvl1": { "id": "palace_cellar_lvl1", "name": "Palace Cellar Lvl 1", "description": "The dark underbelly of the palace.", "requiredLevel": 19, "connectedZoneIds": ["harem_level_1", "harem_level_2", "palace_cellar_lvl2"], "monsterIds": ["returned_archer", "ghoul", "wraith", "gargoyle_trap"] },
  "palace_cellar_lvl2": { "id": "palace_cellar_lvl2", "name": "Palace Cellar Lvl 2", "description": "Deeper into the palace dungeons.", "requiredLevel": 20, "connectedZoneIds": ["palace_cellar_lvl1", "palace_cellar_lvl3"], "monsterIds": ["returned_archer", "bone_fetish", "unraveler", "gargoyle_trap"] },
  "palace_cellar_lvl3": { "id": "palace_cellar_lvl3", "name": "Palace Cellar Lvl 3", "description": "The lowest level, leading to a hidden sanctuary.", "requiredLevel": 21, "connectedZoneIds": ["palace_cellar_lvl2", "arcane_sanctuary"], "monsterIds": ["returned_archer", "unraveler", "hell_swarm", "ghoul"] },
  "arcane_sanctuary": { "id": "arcane_sanctuary", "name": "Arcane Sanctuary", "description": "A bizarre dimension constructed by a mad sorcerer.", "requiredLevel": 22, "connectedZoneIds": ["palace_cellar_lvl3", "canyon_of_the_magi"], "monsterIds": ["hell_clan_goatman", "wraith", "ghoul", "dark_familiar"] },
  "canyon_of_the_magi": { "id": "canyon_of_the_magi", "name": "Canyon of the Magi", "description": "A desolate canyon holding ancient secrets.", "requiredLevel": 24, "connectedZoneIds": ["arcane_sanctuary", "tal_rashas_tomb"], "monsterIds": ["death_beetle", "sand_maggot", "scarab_demon", "pit_viper", "greater_mummy"] },
  "tal_rashas_tomb": { "id": "tal_rashas_tomb", "name": "Tal Rasha's Tomb", "description": "The true tomb, hidden among decoys.", "requiredLevel": 25, "connectedZoneIds": ["canyon_of_the_magi", "forgotten_tombs"], "monsterIds": ["greater_mummy", "unraveler", "scarab_demon", "death_beetle"] },
  "spider_forest": { "id": "spider_forest", "name": "Spider Forest", "description": "A jungle path teeming with arachnids.", "requiredLevel": 21, "connectedZoneIds": ["fetid_jungle", "great_marsh", "spider_cavern"], "monsterIds": ["fetish", "thorned_hulk"] },
  "spider_cavern": { "id": "spider_cavern", "name": "Spider Cavern", "description": "A dark cave, the heart of the spider infestation.", "requiredLevel": 22, "connectedZoneIds": ["spider_forest"], "monsterIds": [] },
  "great_marsh": { "id": "great_marsh", "name": "Great Marsh", "description": "An expansive, treacherous swamp.", "requiredLevel": 22, "connectedZoneIds": ["spider_forest", "flayer_jungle"], "monsterIds": ["fetish", "fen_lurker"] },
  "flayer_jungle": { "id": "flayer_jungle", "name": "Flayer Jungle", "description": "Deep jungle, home to savage Flayer tribes.", "requiredLevel": 23, "connectedZoneIds": ["great_marsh", "flayer_dungeon_lvl1"], "monsterIds": ["flayer", "flayer_shaman", "bone_fetish", "thorned_hulk"] },
  "flayer_dungeon_lvl1": { "id": "flayer_dungeon_lvl1", "name": "Flayer Dungeon Lvl 1", "description": "The upper level of the Flayers' subterranean lair.", "requiredLevel": 24, "connectedZoneIds": ["flayer_jungle", "flayer_dungeon_lvl2"], "monsterIds": ["flayer", "flayer_shaman", "bone_fetish"] },
  "flayer_dungeon_lvl2": { "id": "flayer_dungeon_lvl2", "name": "Flayer Dungeon Lvl 2", "description": "Deeper within the Flayer complex.", "requiredLevel": 25, "connectedZoneIds": ["flayer_dungeon_lvl1", "flayer_dungeon_lvl3"], "monsterIds": ["flayer", "flayer_shaman"] },
  "flayer_dungeon_lvl3": { "id": "flayer_dungeon_lvl3", "name": "Flayer Dungeon Lvl 3", "description": "The heart of the Flayer Dungeon.", "requiredLevel": 26, "connectedZoneIds": ["flayer_dungeon_lvl2", "kurast_causeway"], "monsterIds": ["flayer_shaman"] },
  "kurast_causeway": { "id": "kurast_causeway", "name": "Kurast Causeway", "description": "An ancient stone causeway leading into the heart of Kurast.", "requiredLevel": 30, "connectedZoneIds": ["flayer_dungeon_lvl3", "travincal"], "monsterIds": ["flesh_spawner", "steel_scarab", "hell_clan_goatman"] },
  "travincal": { "id": "travincal", "name": "Travincal", "description": "The corrupted center of the Zakarum faith.", "requiredLevel": 32, "connectedZoneIds": ["kurast_causeway", "durance_of_hate_lvl1"], "monsterIds": ["hierophant", "flesh_hunter"] },
  "durance_of_hate_lvl1": { "id": "durance_of_hate_lvl1", "name": "Durance of Hate Lvl 1", "description": "The upper level of Mephisto's prison.", "requiredLevel": 33, "connectedZoneIds": ["travincal", "durance_of_hate_lvl2"], "monsterIds": ["burning_dead_archer", "flesh_spawner", "stalker", "doom_knight"] },
  "durance_of_hate_lvl2": { "id": "durance_of_hate_lvl2", "name": "Durance of Hate Lvl 2", "description": "Deeper within the prison of hatred.", "requiredLevel": 34, "connectedZoneIds": ["durance_of_hate_lvl1", "durance_of_hate_lvl3"], "monsterIds": ["flesh_hunter", "doom_knight"] },
  "durance_of_hate_lvl3": { "id": "durance_of_hate_lvl3", "name": "Durance of Hate Lvl 3", "description": "Mephisto's inner sanctum.", "requiredLevel": 35, "connectedZoneIds": ["durance_of_hate_lvl2", "infernal_gate"], "monsterIds": ["megademon"] },
  "infernal_gate": { "id": "infernal_gate", "name": "Infernal Gate", "description": "A portal leading to the Burning Hells.", "requiredLevel": 36, "connectedZoneIds": ["durance_of_hate_lvl3", "outer_steppes"], "monsterIds": [] },
  "outer_steppes": { "id": "outer_steppes", "name": "Outer Steppes", "description": "The desolate plains outside the Pandemonium Fortress.", "requiredLevel": 36, "connectedZoneIds": ["infernal_gate", "plains_of_despair"], "monsterIds": ["doom_knight", "megademon", "fingermage", "black_knight", "vile_mother"] },
  "plains_of_despair": { "id": "plains_of_despair", "name": "Plains of Despair", "description": "A cursed land where hope dies.", "requiredLevel": 38, "connectedZoneIds": ["outer_steppes", "city_of_the_damned"], "monsterIds": ["regurgitator", "grotesque", "abyss_knight", "doom_knight", "vile_mother"] },
  "city_of_the_damned": { "id": "city_of_the_damned", "name": "City of the Damned", "description": "The ruined city bordering the River of Flame.", "requiredLevel": 40, "connectedZoneIds": ["plains_of_despair", "river_of_flame"], "monsterIds": ["maw_fiend", "strangler", "storm_caster", "corpulent", "abyss_knight", "hell_templar"] },
  "river_of_flame": { "id": "river_of_flame", "name": "River of Flame", "description": "A burning river leading to the Chaos Sanctuary.", "requiredLevel": 42, "connectedZoneIds": ["city_of_the_damned", "chaos_sanctuary"], "monsterIds": ["blood_lord", "death_mauler", "putrid_defiler", "oblivion_knight", "storm_caster", "maw_fiend"] },
  "chaos_sanctuary": { "id": "chaos_sanctuary", "name": "Chaos Sanctuary", "description": "Diablo's inner sanctum.", "requiredLevel": 45, "connectedZoneIds": ["river_of_flame", "harrogath_gate"], "monsterIds": ["oblivion_knight", "venom_lord", "doom_knight", "storm_caster"] },
  "harrogath_gate": { "id": "harrogath_gate", "name": "Harrogath Gate", "description": "A portal leading to the besieged barbarian city of Harrogath.", "requiredLevel": 46, "connectedZoneIds": ["chaos_sanctuary", "bloody_foothills"], "monsterIds": [] },
  "bloody_foothills": { "id": "bloody_foothills", "name": "Bloody Foothills", "description": "The blood-soaked path leading up Mount Arreat.", "requiredLevel": 46, "connectedZoneIds": ["harrogath_gate", "frigid_highlands"], "monsterIds": ["siege_beast", "death_brigade", "overseer", "imp", "lasher"] },
  "frigid_highlands": { "id": "frigid_highlands", "name": "Frigid Highlands", "description": "A frozen, elevated plain.", "requiredLevel": 48, "connectedZoneIds": ["bloody_foothills", "arreat_plateau"], "monsterIds": ["death_brigade", "blood_bringer", "imp", "abominable", "frozen_horror"] },
  "arreat_plateau": { "id": "arreat_plateau", "name": "Arreat Plateau", "description": "A vast, icy plateau near the summit.", "requiredLevel": 50, "connectedZoneIds": ["frigid_highlands", "crystalline_passage"], "monsterIds": ["blood_bringer", "frozen_horror", "succubus_witch", "minion_of_destruction", "putrid_hound"] },
  "crystalline_passage": { "id": "crystalline_passage", "name": "Crystalline Passage", "description": "A network of icy caves.", "requiredLevel": 51, "connectedZoneIds": ["arreat_plateau", "glacial_trail", "frozen_river"], "monsterIds": ["frozen_horror", "succubus_witch", "death_lord", "stygian_hag", "blood_witch"] },
  "frozen_river": { "id": "frozen_river", "name": "Frozen River", "description": "A hidden river frozen solid within the mountain.", "requiredLevel": 52, "connectedZoneIds": ["crystalline_passage"], "monsterIds": ["frozen_horror", "stygian_hag", "abominable", "succubus_witch"] },
  "glacial_trail": { "id": "glacial_trail", "name": "Glacial Trail", "description": "A treacherous path carved through glaciers.", "requiredLevel": 53, "connectedZoneIds": ["crystalline_passage", "frozen_tundra", "driftwood_cavern"], "monsterIds": ["death_lord", "minion_of_destruction", "stygian_hag", "blood_witch", "pit_lord"] },
  "driftwood_cavern": { "id": "driftwood_cavern", "name": "Driftwood Cavern", "description": "A cave system filled with icy driftwood.", "requiredLevel": 54, "connectedZoneIds": ["glacial_trail"], "monsterIds": ["death_lord", "stygian_hag", "frozen_horror", "putrid_hound"] },
  "frozen_tundra": { "id": "frozen_tundra", "name": "Frozen Tundra", "description": "An expansive, desolate wasteland of ice and snow.", "requiredLevel": 55, "connectedZoneIds": ["glacial_trail", "ancients_way"], "monsterIds": ["pit_lord", "venom_warder", "balrog_demon", "death_caster", "hell_bovine"] },
  "ancients_way": { "id": "ancients_way", "name": "Ancients' Way", "description": "The final path leading to the summit of Mount Arreat.", "requiredLevel": 57, "connectedZoneIds": ["frozen_tundra", "icy_cellar", "arreat_summit"], "monsterIds": ["balrog_demon", "death_caster", "soul_reaver", "moon_lord", "death_sprite"] },
  "icy_cellar": { "id": "icy_cellar", "name": "Icy Cellar", "description": "A hidden cellar beneath the Ancients' Way.", "requiredLevel": 58, "connectedZoneIds": ["ancients_way"], "monsterIds": ["death_caster", "soul_reaver", "stygian_hag", "frozen_horror"] },
  "arreat_summit": { "id": "arreat_summit", "name": "Arreat Summit", "description": "The peak of Mount Arreat, guarded by the Ancients.", "requiredLevel": 59, "connectedZoneIds": ["ancients_way", "worldstone_keep_lvl1"], "monsterIds": [] },
  "worldstone_keep_lvl1": { "id": "worldstone_keep_lvl1", "name": "Worldstone Keep Lvl 1", "description": "The entrance to the Worldstone Keep.", "requiredLevel": 60, "connectedZoneIds": ["arreat_summit", "worldstone_keep_lvl2"], "monsterIds": ["worldstone_guardian", "soul_reaver", "death_lord", "minion_of_destruction", "succubus_witch"] },
  "worldstone_keep_lvl2": { "id": "worldstone_keep_lvl2", "name": "Worldstone Keep Lvl 2", "description": "Deeper within the keep.", "requiredLevel": 60, "connectedZoneIds": ["worldstone_keep_lvl1", "worldstone_keep_lvl3"], "monsterIds": ["worldstone_guardian", "moon_lord", "death_caster", "balrog_demon", "pit_lord"] },
  "worldstone_keep_lvl3": { "id": "worldstone_keep_lvl3", "name": "Worldstone Keep Lvl 3", "description": "Nearing the Throne of Destruction.", "requiredLevel": 60, "connectedZoneIds": ["worldstone_keep_lvl2", "throne_of_destruction"], "monsterIds": ["worldstone_guardian", "death_sprite", "blood_lord", "oblivion_knight", "venom_warder"] },
  "throne_of_destruction": { "id": "throne_of_destruction", "name": "Throne of Destruction", "description": "Baal's throne room.", "requiredLevel": 60, "connectedZoneIds": ["worldstone_keep_lvl3", "worldstone_chamber"], "monsterIds": [] },
  "worldstone_chamber": { "id": "worldstone_chamber", "name": "Worldstone Chamber", "description": "The chamber containing the Worldstone.", "requiredLevel": 60, "connectedZoneIds": ["throne_of_destruction"], "monsterIds": [] }
}
